swanintro/__init__.py
swanintro/_version.py
swanintro/labextension/swan-cern-swanintro-1.0.0.tgz
swanintro/nbextension/extension.js
swanintro/nbextension/img/img1.png
swanintro/nbextension/img/img10.png
swanintro/nbextension/img/img11.png
swanintro/nbextension/img/img12.png
swanintro/nbextension/img/img13.png
swanintro/nbextension/img/img14.png
swanintro/nbextension/img/img2.png
swanintro/nbextension/img/img3.png
swanintro/nbextension/img/img4.png
swanintro/nbextension/img/img5.png
swanintro/nbextension/img/img6.png
swanintro/nbextension/img/img7.png
swanintro/nbextension/img/img8.png
swanintro/nbextension/img/img9.png
swanintro-1.0.0.data/data/share/jupyter/lab/extensions/swan-cern-swanintro-1.0.0.tgz
swanintro-1.0.0.dist-info/METADATA
swanintro-1.0.0.dist-info/WHEEL
swanintro-1.0.0.dist-info/top_level.txt
swanintro-1.0.0.dist-info/RECORD
